cpu/cpu.v
module instruction_decoder(
    input [31:0] instruction,
    output [6:0] opcode,
    output [4:0] rd,
    output [4:0] rs1,
    output [11:0] imm
);
    assign opcode = instruction[6:0];
    assign rd = instruction[11:7];
    assign rs1 = instruction[19:15];
    assign imm = instruction[31:20];
endmodule

module execution_unit(
    input [6:0] opcode,
    input [4:0] rd,
    input [4:0] rs1,
    input [11:0] imm,
    output reg [31:0] result
);
    always @(*) begin
        if (opcode[1:0] == 2'b10) begin
            result = {20'b0, { {7'b0, {rs1}} + imm}};
        end
    end
endmodule

module control_logic(
    input [6:0] opcode,
    output reg [4:0] rd,
    output reg [4:0] rs1,
    output reg [11:0] imm
);
    always @(*) begin
        if (opcode[1:0] == 2'b10) begin
            rd  <= 5'b1;
            rs1 <= 5'b1;
            imm <= 12'b1;
        end
    end
endmodule

module cpu(
    input [31:0] instruction,
    output reg [31:0] result
);
    wire [6:0] opcode; 
    wire [4:0] rd;
    wire [4:0] rs1;
    wire [11:0] imm;

    instruction_decoder ID(
        .instruction(instruction),
        .opcode(opcode),
        .rd(rd),
        .rs1(rs1),
        .imm(imm)
    );

    execution_unit EU(
        .opcode(opcode),
        .rd(rd),
        .rs1(rs1),
        .imm(imm),
        .result(result)
    );

    control_logic CL(
        .opcode(opcode),
        .rd(rd),
        .rs1(rs1),
        .imm(imm)
    );
endmodule

cpu/waveform.vcd
$version Generated by VerilatedVcd $end
$date Tue Dec 13 13:19:27 2022
 $end
$timescale   1ns $end

 $scope module TOP $end
  $var wire 32 ; instruction [31:0] $end
  $var wire 32 C result [31:0] $end
  $scope module cpu $end
   $var wire 12 3 imm [11:0] $end
   $var wire 32 ; instruction [31:0] $end
   $var wire  7 K opcode [6:0] $end
   $var wire  5 # rd [4:0] $end
   $var wire 32 C result [31:0] $end
   $var wire  5 + rs1 [4:0] $end
   $scope module CL $end
    $var wire 12 3 imm [11:0] $end
    $var wire  7 K opcode [6:0] $end
    $var wire  5 # rd [4:0] $end
    $var wire  5 + rs1 [4:0] $end
   $upscope $end
   $scope module EU $end
    $var wire 12 3 imm [11:0] $end
    $var wire  7 K opcode [6:0] $end
    $var wire  5 # rd [4:0] $end
    $var wire 32 C result [31:0] $end
    $var wire  5 + rs1 [4:0] $end
   $upscope $end
   $scope module ID $end
    $var wire 12 3 imm [11:0] $end
    $var wire 32 ; instruction [31:0] $end
    $var wire  7 K opcode [6:0] $end
    $var wire  5 # rd [4:0] $end
    $var wire  5 + rs1 [4:0] $end
   $upscope $end
  $upscope $end
 $upscope $end
$enddefinitions $end


#0
b01010 #
b10100 +
b101010101010 3
b10101010101010100101010101010101 ;
b00000000000000000000000000000000 C
b1010101 K
#1
b00000 #
b00000 +
b000000000000 3
b00000000000000000000000000000000 ;
b0000000 K
#2
b01010 #
b10100 +
b101010101010 3
b10101010101010100101010101010101 ;
b1010101 K
#3
b00000 #
b00000 +
b000000000000 3
b00000000000000000000000000000000 ;
b0000000 K
#4
b01010 #
b10100 +
b101010101010 3
b10101010101010100101010101010101 ;
b1010101 K
#5
b00000 #
b00000 +
b000000000000 3
b00000000000000000000000000000000 ;
b0000000 K
#6
b01010 #
b10100 +
b101010101010 3
b10101010101010100101010101010101 ;
b1010101 K
#7
b00000 #
b00000 +
b000000000000 3
b00000000000000000000000000000000 ;
b0000000 K
#8
b01010 #
b10100 +
b101010101010 3
b10101010101010100101010101010101 ;
b1010101 K
#9
b00000 #
b00000 +
b000000000000 3
b00000000000000000000000000000000 ;
b0000000 K
#10
b01010 #
b10100 +
b101010101010 3
b10101010101010100101010101010101 ;
b1010101 K
#11
b00000 #
b00000 +
b000000000000 3
b00000000000000000000000000000000 ;
b0000000 K
#12
b01010 #
b10100 +
b101010101010 3
b10101010101010100101010101010101 ;
b1010101 K
#13
b00000 #
b00000 +
b000000000000 3
b00000000000000000000000000000000 ;
b0000000 K
#14
b01010 #
b10100 +
b101010101010 3
b10101010101010100101010101010101 ;
b1010101 K
#15
b00000 #
b00000 +
b000000000000 3
b00000000000000000000000000000000 ;
b0000000 K
#16
b01010 #
b10100 +
b101010101010 3
b10101010101010100101010101010101 ;
b1010101 K
#17
b00000 #
b00000 +
b000000000000 3
b00000000000000000000000000000000 ;
b0000000 K
#18
b01010 #
b10100 +
b101010101010 3
b10101010101010100101010101010101 ;
b1010101 K
#19
b00000 #
b00000 +
b000000000000 3
b00000000000000000000000000000000 ;
b0000000 K
